Metadata-Version: 1.2
Name: tutor-figures
Version: 0.2.3
Summary: A Tutor plugin for Figures, the Open edX reporting and data retrieval app
Home-page: https://docs.tutor.overhang.io/
Author: Overhang.io
Author-email: contact@overhang.io
License: AGPLv3
Project-URL: Documentation, https://docs.tutor.overhang.io/
Project-URL: Code, https://github.com/overhangio/tutor-figures
Project-URL: Issue tracker, https://github.com/overhangio/tutor-figures/issues
Project-URL: Community, https://discuss.overhang.io
Platform: UNKNOWN
Classifier: Development Status :: 3 - Alpha
Classifier: Intended Audience :: Developers
Classifier: License :: OSI Approved :: GNU Affero General Public License v3
Classifier: Operating System :: OS Independent
Classifier: Programming Language :: Python
Classifier: Programming Language :: Python :: 3.5
Classifier: Programming Language :: Python :: 3.6
Classifier: Programming Language :: Python :: 3.7
Requires-Python: >=3.5
